imio/__init__.py
imio/scan_helpers/__init__.py
imio/scan_helpers/config.py
imio/scan_helpers/logger.py
imio/scan_helpers/main.py
imio/scan_helpers/profiles_backup.py
imio/scan_helpers/profiles_restore.py
imio/scan_helpers/tests.py
imio/scan_helpers/utils.py
imio_scan_helpers-0.7.0.dist-info/licenses/LICENSE
imio_scan_helpers-0.7.0.dist-info/METADATA
imio_scan_helpers-0.7.0.dist-info/WHEEL
imio_scan_helpers-0.7.0.dist-info/top_level.txt
imio_scan_helpers-0.7.0.dist-info/RECORD
