Metadata-Version: 2.4
Name: imio.scan_helpers
Version: 0.7.0
Summary: Various script files to handle local scan tool
Author: Stephan Geulette (IMIO)
Author-email: support@imio.be
License: GPL version 3
Project-URL: PyPI, https://pypi.python.org/pypi/imio.scan_helpers
Project-URL: Source, https://github.com/IMIO/imio.scan_helpers
Keywords: Scan Windows
Classifier: Development Status :: 3 - Alpha
Classifier: Programming Language :: Python :: 3.12
Classifier: License :: OSI Approved :: GNU General Public License v3 (GPLv3)
Classifier: Operating System :: Microsoft :: Windows
Classifier: Operating System :: Microsoft :: Windows :: Windows 10
Classifier: Operating System :: Microsoft :: Windows :: Windows 11
Requires-Python: >=3.12
License-File: LICENSE
Requires-Dist: pyinstaller
Requires-Dist: requests
Dynamic: author
Dynamic: author-email
Dynamic: classifier
Dynamic: description
Dynamic: keywords
Dynamic: license
Dynamic: license-file
Dynamic: project-url
Dynamic: requires-dist
Dynamic: requires-python
Dynamic: summary
